prophy/__init__.py
prophy/base_array.py
prophy/composite.py
prophy/composite_base.py
prophy/container.py
prophy/descriptor.py
prophy/exception.py
prophy/generators.py
prophy/optional.py
prophy/scalar.py
prophy/six.py
prophyc/__init__.py
prophyc/__main__.py
prophyc/calc.py
prophyc/file_processor.py
prophyc/model.py
prophyc/options.py
prophyc/patch.py
prophyc/six.py
prophyc/generators/__init__.py
prophyc/generators/base.py
prophyc/generators/cpp.py
prophyc/generators/cpp_full.py
prophyc/generators/prophy.py
prophyc/generators/python.py
prophyc/generators/word_wrap.py
prophyc/parsers/__init__.py
prophyc/parsers/isar.py
prophyc/parsers/prophy.py
prophyc/parsers/sack.py
prophyc/parsers/clang/__init__.py
prophyc/parsers/clang/cindex.py
prophyc/parsers/clang/enumerations.py
prophy-1.2.5.dist-info/LICENSE
prophy-1.2.5.dist-info/METADATA
prophy-1.2.5.dist-info/WHEEL
prophy-1.2.5.dist-info/entry_points.txt
prophy-1.2.5.dist-info/top_level.txt
prophy-1.2.5.dist-info/RECORD
